task3/counter.sv
module counter #(
  parameter WIDTH = 8
)(
  // interface signals
  input  logic             clk,      // clock
  input  logic             rst,      // reset
  input  logic             ld,       // load counter from data
  input  logic [WIDTH-1:0] v,        // value to preload
  output logic [WIDTH-1:0] count     // count output
);

always_ff @ (posedge clk, posedge ld)
  if (rst) count <= {WIDTH{1'b0}};
  else     count <= ld ? v : count + {{WIDTH-1{1'b0}},1'b1};
endmodule

task3/counter.vcd
$version Generated by VerilatedVcd $end
$date Sun Nov  3 18:02:13 2024 $end
$timescale 1ps $end

 $scope module TOP $end
  $var wire  1 # clk $end
  $var wire  8 ' count [7:0] $end
  $var wire  1 % ld $end
  $var wire  1 $ rst $end
  $var wire  8 & v [7:0] $end
  $scope module counter $end
   $var wire 32 ( WIDTH [31:0] $end
   $var wire  1 # clk $end
   $var wire  8 ' count [7:0] $end
   $var wire  1 % ld $end
   $var wire  1 $ rst $end
   $var wire  8 & v [7:0] $end
  $upscope $end
 $upscope $end
$enddefinitions $end


#0
1#
1$
0%
b00110011 &
b00000000 '
b00000000000000000000000000001000 (
#1
0#
#2
1#
#3
0#
#4
1#
#5
0#
#6
1#
0$
#7
0#
#8
1#
b00000001 '
#9
0#
#10
1#
b00000010 '
#11
0#
#12
1#
b00000011 '
#13
0#
#14
1#
b00000100 '
#15
0#
#16
1#
b00000101 '
#17
0#
#18
1#
b00000110 '
#19
0#
#20
1#
b00000111 '
#21
0#
#22
1#
b00001000 '
#23
0#
#24
1#
b00001001 '
#25
0#
#26
1#
b00001010 '
#27
0#
#28
1#
b00001011 '
#29
0#
#30
1#
b00001100 '
#31
0#
#32
1#
b00001101 '
#33
0#
#34
1#
b00001110 '
#35
0#
#36
1#
b00001111 '
#37
0#
#38
1#
b00010000 '
#39
0#
#40
1#
b00010001 '
#41
0#
#42
1#
b00010010 '
#43
0#
#44
1#
b00010011 '
#45
0#
#46
1#
b00010100 '
#47
0#
#48
1#
b00010101 '
#49
0#
#50
1#
b00010110 '
#51
0#
#52
1#
b00010111 '
#53
0#
#54
1#
b00011000 '
#55
0#
#56
1#
b00011001 '
#57
0#
#58
1#
b00011010 '
#59
0#
#60
1#
b00011011 '
#61
0#
#62
1#
b00011100 '
#63
0#
#64
1#
b00011101 '
#65
0#
#66
1#
b00011110 '
#67
0#
#68
1#
b00011111 '
#69
0#
#70
1#
b00100000 '
#71
0#
#72
1#
b00100001 '
#73
0#
#74
1#
b00100010 '
#75
0#
#76
1#
b00100011 '
#77
0#
#78
1#
b00100100 '
#79
0#
#80
1#
b00100101 '
#81
0#
#82
1#
b00100110 '
#83
0#
#84
1#
b00100111 '
#85
0#
#86
1#
b00101000 '
#87
0#
#88
1#
b00101001 '
#89
0#
#90
1#
b00101010 '
#91
0#
#92
1#
b00101011 '
#93
0#
#94
1#
b00101100 '
#95
0#
#96
1#
b00101101 '
#97
0#
#98
1#
b00101110 '
#99
0#
#100
1#
b00101111 '
#101
0#
#102
1#
b00110000 '
#103
0#
#104
1#
b00110001 '
#105
0#
#106
1#
b00110010 '
#107
0#
#108
1#
b00110011 '
#109
0#
#110
1#
b00110100 '
#111
0#
#112
1#
b00110101 '
#113
0#
#114
1#
b00110110 '
#115
0#
#116
1#
b00110111 '
#117
0#
#118
1#
b00111000 '
#119
0#
#120
1#
1%
b00111001 '
#121
0#
b00110011 '
#122
1#
0%
#123
0#
#124
1#
b00110100 '
#125
0#
#126
1#
b00110101 '
#127
0#
#128
1#
b00110110 '
#129
0#
#130
1#
b00110111 '
#131
0#
#132
1#
b00111000 '
#133
0#
#134
1#
b00111001 '
#135
0#
#136
1#
b00111010 '
#137
0#
#138
1#
b00111011 '
#139
0#
#140
1#
b00111100 '
#141
0#
#142
1#
b00111101 '
#143
0#
#144
1#
b00111110 '
#145
0#
#146
1#
b00111111 '
#147
0#
#148
1#
b01000000 '
#149
0#
#150
1#
b01000001 '
#151
0#
#152
1#
b01000010 '
#153
0#
#154
1#
b01000011 '
#155
0#
#156
1#
1%
b01000100 '
#157
0#
b00110011 '
#158
1#
0%
#159
0#
#160
1#
b00110100 '
#161
0#
#162
1#
b00110101 '
#163
0#
#164
1#
b00110110 '
#165
0#
#166
1#
b00110111 '
#167
0#
#168
1#
b00111000 '
#169
0#
#170
1#
b00111001 '
#171
0#
#172
1#
b00111010 '
#173
0#
#174
1#
b00111011 '
#175
0#
#176
1#
b00111100 '
#177
0#
#178
1#
b00111101 '
#179
0#
#180
1#
b00111110 '
#181
0#
#182
1#
b00111111 '
#183
0#
#184
1#
b01000000 '
#185
0#
#186
1#
b01000001 '
#187
0#
#188
1#
b01000010 '
#189
0#
#190
1#
b01000011 '
#191
0#
#192
1#
b01000100 '
#193
0#
#194
1#
b01000101 '
#195
0#
#196
1#
b01000110 '
#197
0#
#198
1#
b01000111 '
#199
0#
#200
1#
b01001000 '
#201
0#
#202
1#
b01001001 '
#203
0#
#204
1#
b01001010 '
#205
0#
#206
1#
b01001011 '
#207
0#
#208
1#
b01001100 '
#209
0#
#210
1#
b01001101 '
#211
0#
#212
1#
b01001110 '
#213
0#
#214
1#
b01001111 '
#215
0#
#216
1#
b01010000 '
#217
0#
#218
1#
b01010001 '
#219
0#
#220
1#
b01010010 '
#221
0#
#222
1#
b01010011 '
#223
0#
#224
1#
b01010100 '
#225
0#
#226
1#
b01010101 '
#227
0#
#228
1#
b01010110 '
#229
0#
#230
1#
b01010111 '
#231
0#
#232
1#
b01011000 '
#233
0#
#234
1#
b00110010 &
b01011001 '
#235
0#
#236
1#
b01011010 '
#237
0#
#238
1#
b00110001 &
b01011011 '
#239
0#
#240
1#
b00110000 &
b01011100 '
#241
0#
#242
1#
b00101111 &
b01011101 '
#243
0#
#244
1#
b00101101 &
b01011110 '
#245
0#
#246
1#
b00101100 &
b01011111 '
#247
0#
#248
1#
b00101010 &
b01100000 '
#249
0#
#250
1#
b00101000 &
b01100001 '
#251
0#
#252
1#
b00100111 &
b01100010 '
#253
0#
#254
1#
b00100110 &
b01100011 '
#255
0#
#256
1#
b01100100 '
#257
0#
#258
1#
b01100101 '
#259
0#
#260
1#
b01100110 '
#261
0#
#262
1#
b01100111 '
#263
0#
#264
1#
b01101000 '
#265
0#
#266
1#
b01101001 '
#267
0#
#268
1#
b01101010 '
#269
0#
#270
1#
b01101011 '
#271
0#
#272
1#
b01101100 '
#273
0#
#274
1#
b01101101 '
#275
0#
#276
1#
b01101110 '
#277
0#
#278
1#
b01101111 '
#279
0#
#280
1#
b01110000 '
#281
0#
#282
1#
b01110001 '
#283
0#
#284
1#
b01110010 '
#285
0#
#286
1#
b01110011 '
#287
0#
#288
1#
b01110100 '
#289
0#
#290
1#
1%
b01110101 '
#291
0#
b00100110 '
#292
1#
0%
#293
0#
#294
1#
b00100111 '
#295
0#
#296
1#
b00101000 '
#297
0#
#298
1#
b00101001 '
#299
0#
#300
1#
b00101010 '
#301
0#
#302
1#
b00101011 '
#303
0#
#304
1#
b00101100 '
#305
0#
#306
1#
b00101101 '
#307
0#
#308
1#
b00101110 '
#309
0#
#310
1#
b00101111 '
#311
0#
#312
1#
b00110000 '
#313
0#
#314
1#
b00110001 '
#315
0#
#316
1#
b00110010 '
#317
0#
#318
1#
b00110011 '
#319
0#
#320
1#
b00110100 '
#321
0#
#322
1#
b00110101 '
#323
0#
#324
1#
b00110110 '
#325
0#
#326
1#
b00110111 '
#327
0#
#328
1#
b00111000 '
#329
0#
#330
1#
b00100100 &
b00111001 '
#331
0#
#332
1#
b00100001 &
b00111010 '
#333
0#
#334
1#
b00011111 &
b00111011 '
#335
0#
#336
1#
b00111100 '
#337
0#
#338
1#
b00111101 '
#339
0#
#340
1#
b00111110 '
#341
0#
#342
1#
b00111111 '
#343
0#
#344
1#
b01000000 '
#345
0#
#346
1#
b01000001 '
#347
0#
#348
1#
b01000010 '
#349
0#
#350
1#
b01000011 '
#351
0#
#352
1#
b01000100 '
#353
0#
#354
1#
b01000101 '
#355
0#
#356
1#
b01000110 '
#357
0#
#358
1#
b01000111 '
#359
0#
#360
1#
b01001000 '
#361
0#
#362
1#
1%
b01001001 '
#363
0#
b00011111 '
#364
1#
0%
#365
0#
#366
1#
b00100000 '
#367
0#
#368
1#
b00100001 '
#369
0#
#370
1#
b00100010 '
#371
0#
#372
1#
b00100011 '
#373
0#
#374
1#
b00100100 '
#375
0#
#376
1#
b00100101 '
#377
0#
#378
1#
b00100110 '
#379
0#
#380
1#
b00100111 '
#381
0#
#382
1#
b00101000 '
#383
0#
#384
1#
b00101001 '
#385
0#
#386
1#
b00101010 '
#387
0#
#388
1#
b00101011 '
#389
0#
#390
1#
b00101100 '
#391
0#
#392
1#
b00101101 '
#393
0#
#394
1#
b00101110 '
#395
0#
#396
1#
b00101111 '
#397
0#
#398
1#
b00110000 '
